yoix_pi/__init__.py
yoix_pi/cli.py
yoix_pi/processor.py
yoix_pi-1.0.0.dist-info/LICENSE
yoix_pi-1.0.0.dist-info/METADATA
yoix_pi-1.0.0.dist-info/WHEEL
yoix_pi-1.0.0.dist-info/entry_points.txt
yoix_pi-1.0.0.dist-info/top_level.txt
yoix_pi-1.0.0.dist-info/RECORD
